{"favorited": false, "contributors": null, "truncated": false, "text": "@apple took my Siri and made it exclusive to iPhone 4S  #SoRude", "in_reply_to_status_id": null, "user": {"follow_request_sent": false, "profile_use_background_image": true, "profile_text_color": "333333", "default_profile_image": false, "id": 99587649, "profile_background_image_url_https": "https://pbs.twimg.com/profile_background_images/343087500/index.jpg", "verified": false, "profile_location": null, "profile_image_url_https": "https://pbs.twimg.com/profile_images/422452336896655361/mEO7Xc7D_normal.jpeg", "profile_sidebar_fill_color": "EFEFEF", "entities": {"description": {"urls": []}}, "followers_count": 38, "profile_sidebar_border_color": "EEEEEE", "id_str": "99587649", "profile_background_color": "131516", "listed_count": 0, "is_translation_enabled": false, "utc_offset": null, "statuses_count": 781, "description": "Computer Geek Turned Med Student :) , And like the screen name  Im a Charger Fan ...Not an easy thing to be sometimes lol", "friends_count": 187, "location": "iphone", "profile_link_color": "009999", "profile_image_url": "http://pbs.twimg.com/profile_images/422452336896655361/mEO7Xc7D_normal.jpeg", "following": false, "geo_enabled": true, "profile_background_image_url": "http://pbs.twimg.com/profile_background_images/343087500/index.jpg", "name": "thatchargersfan", "lang": "en", "profile_background_tile": true, "favourites_count": 29, "screen_name": "chargerfan808", "notifications": false, "url": null, "created_at": "Sat Dec 26 22:36:23 +0000 2009", "contributors_enabled": false, "time_zone": null, "protected": false, "default_profile": false, "is_translator": false}, "geo": null, "id": 125245104859529216, "favorite_count": 0, "lang": "en", "source": "<a href=\"http://twitter.com/download/iphone\" rel=\"nofollow\">Twitter for iPhone</a>", "created_at": "Sat Oct 15 16:22:14 +0000 2011", "retweeted": false, "coordinates": null, "in_reply_to_user_id_str": "380749300", "entities": {"symbols": [], "user_mentions": [{"id": 380749300, "indices": [0, 6], "id_str": "380749300", "screen_name": "Apple", "name": "@apple"}], "hashtags": [{"indices": [56, 63], "text": "SoRude"}], "urls": []}, "in_reply_to_status_id_str": null, "in_reply_to_screen_name": "Apple", "id_str": "125245104859529216", "place": null, "retweet_count": 0, "in_reply_to_user_id": 380749300}
