{"favorited": false, "contributors": null, "truncated": false, "text": "@apple Iphone's & Ipad's beautiful technology but alltogether mainly a marketing platform. It's obscure is'nt it? Apple lost it's touch.", "in_reply_to_status_id": null, "user": {"follow_request_sent": false, "profile_use_background_image": true, "profile_text_color": "333333", "default_profile_image": false, "id": 303983009, "profile_background_image_url_https": "https://abs.twimg.com/images/themes/theme1/bg.png", "verified": false, "profile_location": null, "profile_image_url_https": "https://pbs.twimg.com/profile_images/1591044633/fotosmall_normal.JPG", "profile_sidebar_fill_color": "DDEEF6", "entities": {"url": {"urls": [{"url": "http://t.co/NxvOoDrCll", "indices": [0, 22], "expanded_url": "http://www.noorderkwartier.nl/", "display_url": "noorderkwartier.nl"}]}, "description": {"urls": []}}, "followers_count": 12, "profile_sidebar_border_color": "C0DEED", "id_str": "303983009", "profile_background_color": "C0DEED", "listed_count": 0, "is_translation_enabled": false, "utc_offset": 3600, "statuses_count": 15, "description": "", "friends_count": 2, "location": "", "profile_link_color": "0084B4", "profile_image_url": "http://pbs.twimg.com/profile_images/1591044633/fotosmall_normal.JPG", "following": false, "geo_enabled": true, "profile_background_image_url": "http://abs.twimg.com/images/themes/theme1/bg.png", "name": "Jan van Hooff", "lang": "en", "profile_background_tile": false, "favourites_count": 3, "screen_name": "doppelglas", "notifications": false, "url": "http://t.co/NxvOoDrCll", "created_at": "Mon May 23 18:51:39 +0000 2011", "contributors_enabled": false, "time_zone": "Amsterdam", "protected": false, "default_profile": true, "is_translator": false}, "geo": null, "id": 126014214467895297, "favorite_count": 0, "lang": "en", "source": "<a href=\"https://about.twitter.com/products/tweetdeck\" rel=\"nofollow\">TweetDeck</a>", "created_at": "Mon Oct 17 19:18:24 +0000 2011", "retweeted": false, "coordinates": null, "in_reply_to_user_id_str": "380749300", "entities": {"symbols": [], "user_mentions": [{"id": 380749300, "indices": [0, 6], "id_str": "380749300", "screen_name": "Apple", "name": "@apple"}], "hashtags": [], "urls": []}, "in_reply_to_status_id_str": null, "in_reply_to_screen_name": "Apple", "id_str": "126014214467895297", "place": null, "retweet_count": 0, "in_reply_to_user_id": 380749300}
