{"favorited": false, "in_reply_to_user_id": null, "contributors": null, "truncated": false, "text": "Chrome Experiment - WebGL Bookcase - http://t.co/1GNsOwmu #Google", "in_reply_to_status_id": null, "user": {"follow_request_sent": false, "profile_use_background_image": true, "profile_text_color": "333333", "default_profile_image": false, "id": 59542339, "profile_background_image_url_https": "https://abs.twimg.com/images/themes/theme18/bg.gif", "verified": false, "profile_location": null, "profile_image_url_https": "https://pbs.twimg.com/profile_images/486532684177367041/ujr0CmBi_normal.jpeg", "profile_sidebar_fill_color": "F6F6F6", "entities": {"url": {"urls": [{"url": "http://t.co/aqTjdK1u3S", "indices": [0, 22], "expanded_url": "http://twitter.com/nasser2ti", "display_url": "twitter.com/nasser2ti"}]}, "description": {"urls": []}}, "followers_count": 424, "profile_sidebar_border_color": "EEEEEE", "id_str": "59542339", "profile_background_color": "ACDED6", "listed_count": 9, "is_translation_enabled": false, "utc_offset": 10800, "statuses_count": 10498, "description": "MS in Project Management from @CDMDePaul. Love @Alhilal_FC , @acmilan, @chicagobulls , @ChicagoBearscom , @Android & #antiApple \u0645\u0648 \u0639\u0627\u062c\u0628\u0646\u064a \u0648\u0636\u0639 \u0627\u0644\u0628\u0644\u062f", "friends_count": 456, "location": "Riyadh, KSA", "profile_link_color": "038543", "profile_image_url": "http://pbs.twimg.com/profile_images/486532684177367041/ujr0CmBi_normal.jpeg", "following": false, "geo_enabled": false, "profile_banner_url": "https://pbs.twimg.com/profile_banners/59542339/1389797778", "profile_background_image_url": "http://abs.twimg.com/images/themes/theme18/bg.gif", "name": "Nasser Aldarsony", "lang": "en", "profile_background_tile": false, "favourites_count": 319, "screen_name": "nasser2ti", "notifications": false, "url": "http://t.co/aqTjdK1u3S", "created_at": "Thu Jul 23 18:13:48 +0000 2009", "contributors_enabled": false, "time_zone": "Riyadh", "protected": false, "default_profile": false, "is_translator": false}, "geo": null, "id": 126501360089825280, "possibly_sensitive": false, "lang": "en", "source": "<a href=\"http://www.myplume.com/\" rel=\"nofollow\">Plume\u00a0for\u00a0Android</a>", "created_at": "Wed Oct 19 03:34:09 +0000 2011", "retweeted": false, "coordinates": null, "in_reply_to_user_id_str": null, "entities": {"symbols": [], "user_mentions": [], "hashtags": [{"indices": [58, 65], "text": "Google"}], "urls": [{"url": "http://t.co/1GNsOwmu", "indices": [37, 57], "expanded_url": "http://www.youtube.com/watch?v=6GqhJDPi-Ug&feature=youtube_gdata_player", "display_url": "youtube.com/watch?v=6GqhJD\u2026"}]}, "in_reply_to_status_id_str": null, "in_reply_to_screen_name": null, "favorite_count": 0, "place": null, "retweet_count": 0, "id_str": "126501360089825280"}
