{"favorited": false, "contributors": null, "truncated": false, "text": "#GOOGLE #ANDROID 4.0 out ;-) Available with #SAMSUNG nexus!", "in_reply_to_status_id": null, "user": {"follow_request_sent": false, "profile_use_background_image": true, "profile_text_color": "333333", "default_profile_image": false, "id": 148404674, "profile_background_image_url_https": "https://pbs.twimg.com/profile_background_images/434069650372980736/uC2y5Que.jpeg", "verified": false, "profile_location": null, "profile_image_url_https": "https://pbs.twimg.com/profile_images/529468450268123136/IWce3Kky_normal.jpeg", "profile_sidebar_fill_color": "F6F6F6", "entities": {"url": {"urls": [{"url": "http://t.co/lzuKxKOP5j", "indices": [0, 22], "expanded_url": "http://www.facebook.com/catchdoon", "display_url": "facebook.com/catchdoon"}]}, "description": {"urls": []}}, "followers_count": 491, "profile_sidebar_border_color": "FFFFFF", "id_str": "148404674", "profile_background_color": "ACDED6", "listed_count": 7, "is_translation_enabled": false, "utc_offset": 19800, "statuses_count": 27132, "description": "Telecom Engr, ARMINholic, Foodie, Gadgets, Trance/Uplifting Trance/Psy-Trance/Progressive & Techno Lover, Gamer, Sportsperson, Rider, Lives to Drive - 7E3A81D1", "friends_count": 270, "location": "Mumbai", "profile_link_color": "038543", "profile_image_url": "http://pbs.twimg.com/profile_images/529468450268123136/IWce3Kky_normal.jpeg", "following": false, "geo_enabled": true, "profile_banner_url": "https://pbs.twimg.com/profile_banners/148404674/1394803854", "profile_background_image_url": "http://pbs.twimg.com/profile_background_images/434069650372980736/uC2y5Que.jpeg", "name": "A D", "lang": "en", "profile_background_tile": true, "favourites_count": 156, "screen_name": "catch_doon", "notifications": false, "url": "http://t.co/lzuKxKOP5j", "created_at": "Wed May 26 16:21:18 +0000 2010", "contributors_enabled": false, "time_zone": "New Delhi", "protected": false, "default_profile": false, "is_translator": false}, "geo": null, "id": 126521286053724160, "favorite_count": 0, "lang": "en", "source": "<a href=\"http://www.tweets60.com/\" rel=\"nofollow\">Tweets60dm</a>", "created_at": "Wed Oct 19 04:53:19 +0000 2011", "retweeted": false, "coordinates": null, "in_reply_to_user_id_str": null, "entities": {"symbols": [], "user_mentions": [], "hashtags": [{"indices": [0, 7], "text": "GOOGLE"}, {"indices": [8, 16], "text": "ANDROID"}, {"indices": [44, 52], "text": "SAMSUNG"}], "urls": []}, "in_reply_to_status_id_str": null, "in_reply_to_screen_name": null, "id_str": "126521286053724160", "place": null, "retweet_count": 0, "in_reply_to_user_id": null}
