{"favorited": false, "contributors": null, "truncated": false, "text": "\"You don't have to be a computer scientist to use a Windows Phone,\" said #Microsoft 's #SteveBallmer, \"but you do to use an Android phone.\"", "in_reply_to_status_id": null, "user": {"follow_request_sent": false, "profile_use_background_image": true, "profile_text_color": "3C3C3C", "default_profile_image": false, "id": 13038562, "profile_background_image_url_https": "https://pbs.twimg.com/profile_background_images/754248139/617fe134a724a66be88c35c110a5aba6.png", "verified": false, "profile_location": null, "profile_image_url_https": "https://pbs.twimg.com/profile_images/545593461630435328/4dgM-tZ4_normal.jpeg", "profile_sidebar_fill_color": "FFFFFF", "entities": {"url": {"urls": [{"url": "http://t.co/rXEejRuLsG", "indices": [0, 22], "expanded_url": "http://about.me/howbizarre", "display_url": "about.me/howbizarre"}]}, "description": {"urls": []}}, "followers_count": 111, "profile_sidebar_border_color": "000000", "id_str": "13038562", "profile_background_color": "ABC1EB", "listed_count": 7, "is_translation_enabled": false, "utc_offset": 7200, "statuses_count": 2987, "description": "I know everything back from WEB (without a number) to WEB 2.0 and I will keep counting. I am a Front-end Senpai, who strictly follow the W3Code of Bushido :o)", "friends_count": 147, "location": "Sofia, Bulgaria", "profile_link_color": "13B813", "profile_image_url": "http://pbs.twimg.com/profile_images/545593461630435328/4dgM-tZ4_normal.jpeg", "following": false, "geo_enabled": true, "profile_banner_url": "https://pbs.twimg.com/profile_banners/13038562/1418914632", "profile_background_image_url": "http://pbs.twimg.com/profile_background_images/754248139/617fe134a724a66be88c35c110a5aba6.png", "name": "HB's Thinking Usable", "lang": "en", "profile_background_tile": true, "favourites_count": 14, "screen_name": "howbizarre", "notifications": false, "url": "http://t.co/rXEejRuLsG", "created_at": "Mon Feb 04 07:30:48 +0000 2008", "contributors_enabled": false, "time_zone": "Sofia", "protected": false, "default_profile": false, "is_translator": false}, "geo": null, "id": 126674948671545344, "favorite_count": 0, "lang": "en", "source": "<a href=\"http://twitter.com\" rel=\"nofollow\">Twitter Web Client</a>", "created_at": "Wed Oct 19 15:03:55 +0000 2011", "retweeted": false, "coordinates": null, "in_reply_to_user_id_str": null, "entities": {"symbols": [], "user_mentions": [], "hashtags": [{"indices": [73, 83], "text": "Microsoft"}, {"indices": [87, 100], "text": "SteveBallmer"}], "urls": []}, "in_reply_to_status_id_str": null, "in_reply_to_screen_name": null, "id_str": "126674948671545344", "place": null, "retweet_count": 0, "in_reply_to_user_id": null}
