{"favorited": false, "contributors": null, "truncated": false, "text": "#Twitter Off n.n", "in_reply_to_status_id": null, "user": {"follow_request_sent": false, "profile_use_background_image": true, "profile_text_color": "3E4415", "default_profile_image": false, "id": 309295372, "profile_background_image_url_https": "https://abs.twimg.com/images/themes/theme5/bg.gif", "verified": false, "profile_location": null, "profile_image_url_https": "https://pbs.twimg.com/profile_images/540395396644622337/4wol8EeN_normal.jpeg", "profile_sidebar_fill_color": "99CC33", "entities": {"url": {"urls": [{"url": "http://t.co/GYdiqpPz9i", "indices": [0, 22], "expanded_url": "http://instagram.com/earthtofernanda", "display_url": "instagram.com/earthtofernanda"}]}, "description": {"urls": []}}, "followers_count": 173, "profile_sidebar_border_color": "829D5E", "id_str": "309295372", "profile_background_color": "352726", "listed_count": 0, "is_translation_enabled": false, "utc_offset": -28800, "statuses_count": 5762, "description": "forget not the earth delights to feel your bare feet and the winds long to play with your hair", "friends_count": 48, "location": "wonderland ", "profile_link_color": "D02B55", "profile_image_url": "http://pbs.twimg.com/profile_images/540395396644622337/4wol8EeN_normal.jpeg", "following": false, "geo_enabled": true, "profile_banner_url": "https://pbs.twimg.com/profile_banners/309295372/1415246902", "profile_background_image_url": "http://abs.twimg.com/images/themes/theme5/bg.gif", "name": "fernie fern fern \u0950", "lang": "en", "profile_background_tile": false, "favourites_count": 316, "screen_name": "EarthToFernanda", "notifications": false, "url": "http://t.co/GYdiqpPz9i", "created_at": "Wed Jun 01 21:19:07 +0000 2011", "contributors_enabled": false, "time_zone": "Pacific Time (US & Canada)", "protected": false, "default_profile": false, "is_translator": false}, "geo": null, "id": 126878811009728513, "favorite_count": 0, "lang": "en", "source": "<a href=\"http://twitter.com/download/android\" rel=\"nofollow\">Twitter for Android</a>", "created_at": "Thu Oct 20 04:34:00 +0000 2011", "retweeted": false, "coordinates": null, "in_reply_to_user_id_str": null, "entities": {"symbols": [], "user_mentions": [], "hashtags": [{"indices": [0, 8], "text": "Twitter"}], "urls": []}, "in_reply_to_status_id_str": null, "in_reply_to_screen_name": null, "id_str": "126878811009728513", "place": null, "retweet_count": 0, "in_reply_to_user_id": null}
